tag_images_for_google_drive/__init__.py
tag_images_for_google_drive/exiftool.py
tag_images_for_google_drive/py.typed
tag_images_for_google_drive/tag_images_for_google_drive.py
tag_images_for_google_drive/tools.py
tests/__init__.py
tests/test_tag_images_for_google_drive.py
tag_images_for_google_drive-1.1.dist-info/LICENSE
tag_images_for_google_drive-1.1.dist-info/METADATA
tag_images_for_google_drive-1.1.dist-info/WHEEL
tag_images_for_google_drive-1.1.dist-info/entry_points.txt
tag_images_for_google_drive-1.1.dist-info/top_level.txt
tag_images_for_google_drive-1.1.dist-info/zip-safe
tag_images_for_google_drive-1.1.dist-info/RECORD
