Metadata-Version: 2.1
Name: tag-images-for-google-drive
Version: 1.1
Summary: Manage tags and description to be indexed by Google Drive
Home-page: http://github.com/pprados/tag_images_for_google_drive
Author: Philippe PRADOS
Author-email: github@prados.fr
License: Apache License
Keywords: image index google drive
Platform: UNKNOWN
Classifier: Development Status :: 5 - Production/Stable
Classifier: Environment :: Console
Classifier: Intended Audience :: End Users/Desktop
Classifier: License :: OSI Approved
Classifier: Natural Language :: English
Classifier: Programming Language :: Python :: 3.7
Classifier: Operating System :: OS Independent
Classifier: Topic :: Scientific/Engineering :: Artificial Intelligence
Requires-Python: ~=3.7
License-File: LICENSE
Requires-Dist: click
Requires-Dist: click-pathlib
Provides-Extra: dev
Requires-Dist: pip ; extra == 'dev'
Requires-Dist: twine ; extra == 'dev'
Requires-Dist: sphinx ; extra == 'dev'
Requires-Dist: sphinx-execute-code ; extra == 'dev'
Requires-Dist: sphinx-rtd-theme ; extra == 'dev'
Requires-Dist: recommonmark ; extra == 'dev'
Requires-Dist: nbsphinx ; extra == 'dev'
Requires-Dist: flake8 ; extra == 'dev'
Requires-Dist: pylint ; extra == 'dev'
Requires-Dist: PyInstaller ; extra == 'dev'
Requires-Dist: daff ; extra == 'dev'
Requires-Dist: mypy ; extra == 'dev'
Provides-Extra: test
Requires-Dist: pytest (>=2.8.0) ; extra == 'test'
Requires-Dist: pytest-openfiles ; extra == 'test'
Requires-Dist: pytest-xdist ; extra == 'test'
Requires-Dist: pytest-mock ; extra == 'test'
Requires-Dist: unittest2 ; extra == 'test'
